{
    "Gers": {
        "2016": "gers_ocsge_2016.zip",
        "2016_zc": "gers_zone_construite_2016.zip",
        "2019": "gers_ocsge_2019.zip",
        "2019_zc": "gers_zone_construite_2019.zip",
        "2016_2019_diff": {
            "path": "gers_ocsge_2016_2019_diff.zip",
            "mapping": {
                "cs_old": "cs_apres",
                "us_old": "us_apres",
                "cs_new": "cs_avant",
                "us_new": "us_avant",
                "mpoly": "MULTIPOLYGON"
            }
        }
    },
    "Essonne": {
        "2016": "essonne_ocsge_2016.zip",
        "2016_zc": "essonne_zone_construite_2016.zip",
        "2019": "essonne_ocsge_2019.zip",
        "2019_zc": "essonne_zone_construite_2019.zip",
        "2016_2019_diff": "essonne_ocsge_2016_2019_diff.zip"
    }
}